visual_tree/VisualTree.py
visual_tree/__init__.py
visual_tree-1.0.1.dist-info/LICENSE
visual_tree-1.0.1.dist-info/METADATA
visual_tree-1.0.1.dist-info/WHEEL
visual_tree-1.0.1.dist-info/top_level.txt
visual_tree-1.0.1.dist-info/RECORD
