Metadata-Version: 2.1
Name: visual-tree
Version: 1.0.1
Summary: visualize the tree structure of any recursable object in python
Home-page: https://github.com/Nocretsis/visual-tree
Author: Nocsis
Author-email: cchj2638@gmail.com
Classifier: Programming Language :: Python :: 3
Classifier: License :: OSI Approved :: Apache Software License
Classifier: Operating System :: OS Independent
Classifier: Topic :: Software Development :: Libraries :: Python Modules
Classifier: Topic :: Utilities
Requires-Python: >=3.8
License-File: LICENSE
